pyfinder/__init__.py
pyfinder/cache.py
pyfinder/core.py
pyfinder/detectors.py
pyfinder/runner.py
pyfinder/split_runner.py
pyfinder/utils.py
pyfinder_tool-0.3.4.dist-info/licenses/LICENSE
pyfinder_tool-0.3.4.dist-info/METADATA
pyfinder_tool-0.3.4.dist-info/WHEEL
pyfinder_tool-0.3.4.dist-info/entry_points.txt
pyfinder_tool-0.3.4.dist-info/top_level.txt
pyfinder_tool-0.3.4.dist-info/RECORD
