Metadata-Version: 2.4
Name: pyfinder-tool
Version: 0.3.4
Summary: 一个强大的Python环境搜索与运行工具包
Home-page: https://github.com/pyfinder/pyfinder
Author: PyFinder Team
Author-email: PyFinder Team <pyfinder@example.com>
License: MIT
Project-URL: Homepage, https://github.com/pyfinder/pyfinder
Project-URL: Repository, https://github.com/pyfinder/pyfinder.git
Project-URL: Documentation, https://pyfinder.readthedocs.io/
Project-URL: Bug Tracker, https://github.com/pyfinder/pyfinder/issues
Keywords: python,environment,finder,runner,venv,conda,uv
Classifier: Development Status :: 4 - Beta
Classifier: Intended Audience :: Developers
Classifier: License :: OSI Approved :: MIT License
Classifier: Operating System :: OS Independent
Classifier: Programming Language :: Python :: 3
Classifier: Programming Language :: Python :: 3.7
Classifier: Programming Language :: Python :: 3.8
Classifier: Programming Language :: Python :: 3.9
Classifier: Programming Language :: Python :: 3.10
Classifier: Programming Language :: Python :: 3.11
Classifier: Programming Language :: Python :: 3.12
Classifier: Topic :: Software Development :: Libraries :: Python Modules
Classifier: Topic :: System :: Systems Administration
Classifier: Topic :: Utilities
Requires-Python: >=3.7
License-File: LICENSE
Provides-Extra: dev
Requires-Dist: pytest>=6.0; extra == "dev"
Requires-Dist: pytest-cov>=2.0; extra == "dev"
Requires-Dist: black>=21.0; extra == "dev"
Requires-Dist: flake8>=3.8; extra == "dev"
Requires-Dist: mypy>=0.800; extra == "dev"
Dynamic: author
Dynamic: home-page
Dynamic: license-file
Dynamic: requires-python
